BigBank/__init__.py
BigBank/bigbank.py
bigbank-0.1.4.dist-info/METADATA
bigbank-0.1.4.dist-info/WHEEL
bigbank-0.1.4.dist-info/top_level.txt
bigbank-0.1.4.dist-info/RECORD
