Metadata-Version: 2.1
Name: bigbank
Version: 0.1.4
Summary: Really useless library that has no reason to exist !!!
Home-page: https://github.com/developer-cunningham/bigbank
Author: William Cunningham
Author-email: mrcoolguy640@example.com
Classifier: Programming Language :: Python :: 3
Classifier: License :: OSI Approved :: MIT License
Classifier: Operating System :: OS Independent
Requires-Python: >=3.6
